NgspicetoModelica.py
README.txt
setup.py
ngspiceToModelica.egg-info/PKG-INFO
ngspiceToModelica.egg-info/SOURCES.txt
ngspiceToModelica.egg-info/dependency_links.txt
ngspiceToModelica.egg-info/top_level.txt